slurmformspawner/__init__.py
slurmformspawner/form.py
slurmformspawner/slurm.py
slurmformspawner/spawner.py
slurmformspawner/traitlets.py
slurmformspawner-2.9.2.data/data/share/slurmformspawner/templates/error.html
slurmformspawner-2.9.2.data/data/share/slurmformspawner/templates/form.html
slurmformspawner-2.9.2.data/data/share/slurmformspawner/templates/submit.sh
slurmformspawner-2.9.2.dist-info/licenses/LICENSE
slurmformspawner-2.9.2.dist-info/METADATA
slurmformspawner-2.9.2.dist-info/WHEEL
slurmformspawner-2.9.2.dist-info/top_level.txt
slurmformspawner-2.9.2.dist-info/RECORD
