Metadata-Version: 2.4
Name: slurmformspawner
Version: 2.9.2
Summary: slurmformspawner: JupyterHub SlurmSpawner with a dynamic spawn form
Home-page: https://github.com/cmd-ntrf/slurmformspawner
Author: Félix-Antoine Fortin
Author-email: felix-antoine.fortin@calculquebec.ca
License: MIT
Keywords: Interactive,Web,JupyterHub
Platform: Linux
Platform: Mac OS X
Classifier: Intended Audience :: Developers
Classifier: Intended Audience :: System Administrators
Classifier: Intended Audience :: Science/Research
Classifier: License :: OSI Approved :: BSD License
Classifier: Programming Language :: Python
Classifier: Programming Language :: Python :: 3
License-File: LICENSE
Requires-Dist: batchspawner>=1.3.0
Requires-Dist: WTForms==2.3.1
Requires-Dist: jinja2>=2.10.1
Requires-Dist: cachetools
Dynamic: author
Dynamic: author-email
Dynamic: classifier
Dynamic: description
Dynamic: description-content-type
Dynamic: home-page
Dynamic: keywords
Dynamic: license
Dynamic: license-file
Dynamic: platform
Dynamic: requires-dist
Dynamic: summary
